TonyBotV1/__init__.py
TonyBotV1/datasets/__init__.py
TonyBotV1/datasets/utils.py
TonyBotV1/datasets/data/GBPUSD15.csv
TonyBotV1/datasets/data/GBPUSD60.csv
TonyBotV1/envs/__init__.py
TonyBotV1/envs/gym_TonyBot.py
TonyBotV1-1.1.0.dist-info/LICENSE.txt
TonyBotV1-1.1.0.dist-info/METADATA
TonyBotV1-1.1.0.dist-info/WHEEL
TonyBotV1-1.1.0.dist-info/top_level.txt
TonyBotV1-1.1.0.dist-info/RECORD
