Metadata-Version: 2.1
Name: TonyBotV1
Version: 1.1.0
Summary: UNKNOWN
Home-page: UNKNOWN
Author: VEGETA_777
Author-email: xguru.vn@gmail.com
License: MIT
Platform: UNKNOWN
Requires-Dist: gym (>=0.12.5)
Requires-Dist: numpy (>=1.16.4)
Requires-Dist: pandas (>=0.24.2)
Requires-Dist: matplotlib (>=3.1.1)
